setup.py
ssx/__init__.py
ssx.egg-info/PKG-INFO
ssx.egg-info/SOURCES.txt
ssx.egg-info/dependency_links.txt
ssx.egg-info/top_level.txt