Metadata-Version: 1.0
Name: ssx
Version: 0.0.1
Summary: Synchrotron serial crystallography tools
Home-page: https://github.com/kif/ssx
Author: Jerome Kieffer
Author-email: jerome.kieffer@esrf.fr
License: UNKNOWN
Platform: UNKNOWN
